pypet2bids/Pipfile
pypet2bids/README.md
pypet2bids/__init__.py
pypet2bids/convert_pmod_to_blood.py
pypet2bids/dcm2niix4pet.py
pypet2bids/ecat.py
pypet2bids/ecat2nii.py
pypet2bids/ecat_cli.py
pypet2bids/ecat_header_update.py
pypet2bids/ecat_headers.json
pypet2bids/golden_ecat.py
pypet2bids/helper_functions.py
pypet2bids/is_pet.py
pypet2bids/metadata_spreadsheet_example_reader.py
pypet2bids/multiple_spreadsheets.py
pypet2bids/pet_metadata.py
pypet2bids/pyproject.toml
pypet2bids/read_ecat.py
pypet2bids/sidecar.py
pypet2bids/single_spreadsheet.py
pypet2bids/telemetry.py
pypet2bids/template.env
pypet2bids/template_json.json
pypet2bids/update_json_pet_file.py
pypet2bids/write_ecat.py
pypet2bids/dcm2niix_binaries/dcm2niix_lnx.zip
pypet2bids/dcm2niix_binaries/dcm2niix_mac.zip
pypet2bids/dcm2niix_binaries/dcm2niix_win.zip
pypet2bids-1.4.6.dist-info/METADATA
pypet2bids-1.4.6.dist-info/WHEEL
pypet2bids-1.4.6.dist-info/entry_points.txt
pypet2bids-1.4.6.dist-info/RECORD
