Metadata-Version: 2.4
Name: pypet2bids
Version: 1.4.6
Summary: A python library for converting PET imaging and blood data to BIDS.
Project-URL: Documentation, https://pypet2bids.readthedocs.io/en/latest/
Project-URL: Repository, https://github.com/openneuropet/pet2bids/
Author-email: anthony galassi <28850131+bendhouseart@users.noreply.github.com>
License: MIT
Classifier: Development Status :: 4 - Beta
Classifier: Intended Audience :: Science/Research
Classifier: License :: OSI Approved :: MIT License
Classifier: Programming Language :: Python :: 3
Classifier: Programming Language :: Python :: 3.8
Classifier: Programming Language :: Python :: 3.9
Classifier: Programming Language :: Python :: 3.10
Classifier: Programming Language :: Python :: 3.11
Classifier: Programming Language :: Python :: 3.12
Classifier: Programming Language :: Python :: 3.13
Requires-Python: >=3.8
Requires-Dist: joblib>=1.2.0
Requires-Dist: json-maj>=0.0.8
Requires-Dist: nibabel>=3.2.1
Requires-Dist: numpy>=1.21.3
Requires-Dist: openpyxl>=3.0.9
Requires-Dist: pandas>=1.4.4
Requires-Dist: pydicom>=2.2.2
Requires-Dist: pyparsing>=3.0.4
Requires-Dist: python-dateutil>=2.8.2
Requires-Dist: python-dotenv>=0.19.1
Requires-Dist: pyxlsb>=1.0.9
Requires-Dist: requests>=2.32.3
Requires-Dist: scipy>=1.7.1
Requires-Dist: six>=1.16.0
Requires-Dist: toml>=0.10.2
Requires-Dist: xlrd>=2.0.1
Provides-Extra: dev
Requires-Dist: black>=23.0.0; extra == 'dev'
Requires-Dist: briefcase>=0.3.23; (python_version >= '3.9') and extra == 'dev'
Requires-Dist: build>=0.10.0; extra == 'dev'
Requires-Dist: pyinstaller>=5.4.1; extra == 'dev'
Requires-Dist: pytest<8.0.0,>=6.2.5; extra == 'dev'
Requires-Dist: sphinx-rtd-theme>=1.2.2; extra == 'dev'
Requires-Dist: sphinx<7.0.0,>=5.0.0; extra == 'dev'
Requires-Dist: sphinxcontrib-matlabdomain>=0.21.4; extra == 'dev'
